pyethnicity/__init__.py
pyethnicity/_bayesian_models.py
pyethnicity/_ml_models.py
pyethnicity/py.typed
pyethnicity/data/distributions/prob_block_group_given_race_2020.parquet
pyethnicity/data/distributions/prob_first_name_given_race.parquet
pyethnicity/data/distributions/prob_race_given_block_group_2020.parquet
pyethnicity/data/distributions/prob_race_given_first_name.parquet
pyethnicity/data/distributions/prob_race_given_last_name.parquet
pyethnicity/data/distributions/prob_race_given_tract_2020.parquet
pyethnicity/data/distributions/prob_race_given_zcta_2020.parquet
pyethnicity/data/distributions/prob_tract_given_race_2020.parquet
pyethnicity/data/distributions/prob_zcta_given_race_2020.parquet
pyethnicity/data/distributions/ssa.parquet
pyethnicity/data/distributions/6cat/prob_first_name_given_race.parquet
pyethnicity/data/distributions/6cat/prob_race_given_first_name.parquet
pyethnicity/data/distributions/6cat/prob_race_given_last_name.parquet
pyethnicity/utils/__init__.py
pyethnicity/utils/paths.py
pyethnicity/utils/types.py
pyethnicity/utils/utils.py
pyethnicity-0.0.27.dist-info/licenses/LICENSE
pyethnicity-0.0.27.dist-info/METADATA
pyethnicity-0.0.27.dist-info/WHEEL
pyethnicity-0.0.27.dist-info/top_level.txt
pyethnicity-0.0.27.dist-info/RECORD
