Metadata-Version: 2.4
Name: pyethnicity
Version: 0.0.27
Summary: Predict race from name and location
Home-page: https://github.com/CangyuanLi/pyethnicity
Author: Cangyuan Li
Author-email: everest229@gmail.com
Project-URL: Bug Tracker, https://github.com/CangyuanLi/pyethnicity/issues
Project-URL: Documentation, https://pyethnicity.readthedocs.io/en/latest/
Project-URL: Paper, https://arxiv.org/pdf/2307.08496.pdf
Classifier: Programming Language :: Python :: 3
Classifier: License :: OSI Approved :: MIT License
Classifier: Operating System :: OS Independent
Requires-Python: >=3.6
License-File: LICENSE
Requires-Dist: onnxruntime; platform_system == "Darwin"
Requires-Dist: onnxruntime-gpu; platform_system == "Windows" or platform_system == "Linux"
Requires-Dist: polars>=1.0.0
Requires-Dist: pyarrow
Requires-Dist: pycutils
Requires-Dist: requests
Requires-Dist: tqdm
Dynamic: license-file
